grass_rag/__init__.py
grass_rag/cli/__init__.py
grass_rag/cli/main.py
grass_rag/cli/ui.py
grass_rag/core/__init__.py
grass_rag/core/cache.py
grass_rag/core/models.py
grass_rag/core/pipeline.py
grass_rag/core/templates.py
grass_rag/data/__init__.py
grass_rag/data/templates.json
grass_rag/utils/__init__.py
grass_rag/utils/compression.py
grass_rag/utils/download.py
grass_rag/utils/platform.py
grass_rag/utils/validation.py
grass_rag_pipeline-1.0.4.dist-info/licenses/LICENSE
grass_rag_pipeline-1.0.4.dist-info/METADATA
grass_rag_pipeline-1.0.4.dist-info/WHEEL
grass_rag_pipeline-1.0.4.dist-info/entry_points.txt
grass_rag_pipeline-1.0.4.dist-info/top_level.txt
grass_rag_pipeline-1.0.4.dist-info/RECORD
