Metadata-Version: 2.4
Name: grass-rag-pipeline
Version: 1.0.4
Summary: High-performance RAG pipeline for GRASS GIS with >90% accuracy and <5s response time
Home-page: https://github.com/Sachin-NK/grass-rag-pipeline
Author: Sachin-NK
Author-email: snkodijara52@gmail.com
License: MIT
Project-URL: Bug Reports, https://github.com/Sachin-NK/grass-rag-pipeline/issues
Project-URL: Source, https://github.com/Sachin-NK/grass-rag-pipeline
Project-URL: Documentation, https://github.com/Sachin-NK/grass-rag-pipeline/blob/main/README.md
Project-URL: Changelog, https://github.com/Sachin-NK/grass-rag-pipeline/blob/main/CHANGELOG.md
Keywords: grass-gis,rag,retrieval-augmented-generation,gis,geospatial,ai,machine-learning,vector-database,semantic-search,llm,chatbot,question-answering,template-matching,performance-optimized,offline-capable
Platform: any
Classifier: Development Status :: 5 - Production/Stable
Classifier: Intended Audience :: Science/Research
Classifier: Intended Audience :: Developers
Classifier: Topic :: Scientific/Engineering :: GIS
Classifier: Topic :: Scientific/Engineering :: Artificial Intelligence
Classifier: Topic :: Software Development :: Libraries :: Python Modules
Classifier: License :: OSI Approved :: MIT License
Classifier: Programming Language :: Python :: 3
Classifier: Programming Language :: Python :: 3.8
Classifier: Programming Language :: Python :: 3.9
Classifier: Programming Language :: Python :: 3.10
Classifier: Programming Language :: Python :: 3.11
Classifier: Programming Language :: Python :: 3.12
Classifier: Operating System :: OS Independent
Classifier: Environment :: Console
Classifier: Environment :: Web Environment
Requires-Python: >=3.8
License-File: LICENSE
Requires-Dist: torch<3.0.0,>=2.0.0
Requires-Dist: transformers<5.0.0,>=4.30.0
Requires-Dist: sentence-transformers<3.0.0,>=2.2.0
Requires-Dist: numpy<2.0.0,>=1.24.0
Requires-Dist: lancedb<1.0.0,>=0.3.0
Requires-Dist: pyarrow<15.0.0,>=12.0.0
Requires-Dist: loguru<1.0.0,>=0.7.0
Requires-Dist: click<9.0.0,>=8.1.0
Requires-Dist: pandas<3.0.0,>=2.0.0
Requires-Dist: tqdm<5.0.0,>=4.65.0
Requires-Dist: requests<3.0.0,>=2.31.0
Requires-Dist: psutil<6.0.0,>=5.9.0
Provides-Extra: ui
Requires-Dist: streamlit<2.0.0,>=1.25.0; extra == "ui"
Requires-Dist: plotly<6.0.0,>=5.15.0; extra == "ui"
Provides-Extra: dev
Requires-Dist: pytest<8.0.0,>=7.4.0; extra == "dev"
Requires-Dist: pytest-asyncio<1.0.0,>=0.21.0; extra == "dev"
Requires-Dist: pytest-cov<5.0.0,>=4.1.0; extra == "dev"
Requires-Dist: black<24.0.0,>=23.0.0; extra == "dev"
Requires-Dist: isort<6.0.0,>=5.12.0; extra == "dev"
Requires-Dist: flake8<7.0.0,>=6.0.0; extra == "dev"
Provides-Extra: monitoring
Requires-Dist: prometheus-client<1.0.0,>=0.17.0; extra == "monitoring"
Provides-Extra: rich
Requires-Dist: rich<14.0.0,>=13.0.0; extra == "rich"
Provides-Extra: full
Requires-Dist: streamlit<2.0.0,>=1.25.0; extra == "full"
Requires-Dist: plotly<6.0.0,>=5.15.0; extra == "full"
Requires-Dist: pytest<8.0.0,>=7.4.0; extra == "full"
Requires-Dist: pytest-asyncio<1.0.0,>=0.21.0; extra == "full"
Requires-Dist: pytest-cov<5.0.0,>=4.1.0; extra == "full"
Requires-Dist: black<24.0.0,>=23.0.0; extra == "full"
Requires-Dist: isort<6.0.0,>=5.12.0; extra == "full"
Requires-Dist: flake8<7.0.0,>=6.0.0; extra == "full"
Requires-Dist: prometheus-client<1.0.0,>=0.17.0; extra == "full"
Requires-Dist: rich<14.0.0,>=13.0.0; extra == "full"
Provides-Extra: test
Requires-Dist: pytest>=7.4.0; extra == "test"
Requires-Dist: pytest-asyncio>=0.21.0; extra == "test"
Requires-Dist: pytest-cov>=4.1.0; extra == "test"
Requires-Dist: psutil>=5.9.0; extra == "test"
Dynamic: author
Dynamic: author-email
Dynamic: classifier
Dynamic: description
Dynamic: description-content-type
Dynamic: home-page
Dynamic: keywords
Dynamic: license
Dynamic: license-file
Dynamic: platform
Dynamic: project-url
Dynamic: provides-extra
Dynamic: requires-dist
Dynamic: requires-python
Dynamic: summary
